<object-stream>
  <com.billkuker.rocketry.motorsim.Motor>
    <chamber class="com.billkuker.rocketry.motorsim.cases.Schedule40">
      <length>43 cm</length>
      <size>TwoInch</size>
    </chamber>
    <fuel class="com.billkuker.rocketry.motorsim.fuel.KNSU" serialization="custom">
      <java.net.URI>
        <default>
          <string>motorsim:KNSU</string>
        </default>
      </java.net.URI>
    </fuel>
    <grain class="com.billkuker.rocketry.motorsim.grain.MultiGrain">
      <count>4</count>
      <grain class="com.billkuker.rocketry.motorsim.grain.CoredCylindricalGrain">
        <ID>1 cm</ID>
        <OD>4.34 cm</OD>
        <aftEndInhibited>false</aftEndInhibited>
        <foreEndInhibited>false</foreEndInhibited>
        <innerSurfaceInhibited>false</innerSurfaceInhibited>
        <length>10 cm</length>
        <outerSurfaceInhibited>true</outerSurfaceInhibited>
      </grain>
      <spacing>6 mm</spacing>
    </grain>
    <name>DeathMotor</name>
    <nozzle class="com.billkuker.rocketry.motorsim.ConvergentDivergentNozzle">
      <efficiency>0.85</efficiency>
      <exitDiameter>4.34 cm</exitDiameter>
      <throatDiameter>1.25 cm</throatDiameter>
    </nozzle>
  </com.billkuker.rocketry.motorsim.Motor>
</object-stream>
